nodepsutils/README.MD
nodepsutils/__init__.py
nodepsutils/requirements.txt
nodepsutils/thirdparty.json
nodepsutils-0.10.dist-info/LICENSE.rst
nodepsutils-0.10.dist-info/METADATA
nodepsutils-0.10.dist-info/WHEEL
nodepsutils-0.10.dist-info/top_level.txt
nodepsutils-0.10.dist-info/RECORD
