Metadata-Version: 2.1
Name: nodepsutils
Version: 0.10
Summary: Some utilities made with the standard library - Windows only
Home-page: https://github.com/hansalemaos/nodepsutils
Author: Johannes Fischer
Author-email: aulasparticularesdealemaosp@gmail.com
License: MIT
Keywords: utils
Classifier: Development Status :: 4 - Beta
Classifier: Programming Language :: Python :: 3 :: Only
Classifier: Programming Language :: Python :: 3.10
Classifier: Topic :: Software Development :: Libraries :: Python Modules
Classifier: Topic :: Utilities
License-File: LICENSE.rst
